tpds_extension/ip_protection/extension.yaml
tpds_extension/ip_protection/setup.py
tpds_extension/ip_protection/version.py
tpds_extension/ip_protection/TrustFlex/IP Protection.ipynb
tpds_extension/ip_protection/TrustFlex/firmware.zip
tpds_extension/ip_protection/TrustFlex/slot_5_secret_key.h
tpds_extension/ip_protection/TrustFlex/assets/IP Protection.md
tpds_extension/ip_protection/TrustFlex/assets/IP protection.png
tpds_extension/ip_protection/TrustFlex/assets/c-snippet.png
tpds_extension/ip_protection/TrustFlex/assets/crypto-assets.png
tpds_extension/ip_protection/TrustFlex/assets/td_ip_protection.png
tpds_extension/ip_protection/TrustFlex/assets/usecase_steps.png
tpds_extension/ip_protection/TrustFlex/assets/python/LICENSE
tpds_extension/ip_protection/TrustFlex/assets/python/README.md
tpds_extension/ip_protection/TrustFlex/assets/python/__init__.py
tpds_extension/ip_protection/TrustFlex/assets/python/requirements.txt
tpds_extension/ip_protection/TrustFlex/assets/python/setup.py
tpds_extension/ip_protection/TrustFlex/assets/python/ip_protection/__init__.py
tpds_extension/ip_protection/TrustFlex/assets/python/ip_protection/ip_protection.py
tpds_extension_spg_ip_protection-2.2.3.dist-info/METADATA
tpds_extension_spg_ip_protection-2.2.3.dist-info/WHEEL
tpds_extension_spg_ip_protection-2.2.3.dist-info/top_level.txt
tpds_extension_spg_ip_protection-2.2.3.dist-info/RECORD
